[
  {
    "id": 1,
    "parentId": null,
    "name": "Software Engineering"
  },
  {
    "id": 2,
    "parentId": 1,
    "name": "Frontend"
  },
  {
    "id": 3,
    "parentId": 2,
    "name": "React",
    "postIds": [1,2]
  },
  {
    "id": 4,
    "parentId": 1,
    "name": "Backend",
    "postIds": [3,4]
  },
  {
    "id": 5,
    "parentId": null,
    "name": "Finances"
  },
  {
    "id": 6,
    "parentId": 5,
    "name": "Money"
  },
  {
    "id": 7,
    "parentId": 6,
    "name": "Sub-Sub Department 1",
    "postIds": [5,6]
  },
  {
    "id": 8,
    "parentId": 5,
    "name": "Sub Department 2",
    "postIds": [7,8]
  }
]
